[
  {
    "name": "Serge Gnabry",
    "birthday": "1995-7-14",
    "thumbnail": {
      "source": "https://upload.wikimedia.org/wikipedia/commons/thumb/9/9b/Serge_Gnabry_Training_2019-09-01_FC_Bayern_Muenchen-1_%28cropped%29.jpg/245px-Serge_Gnabry_Training_2019-09-01_FC_Bayern_Muenchen-1_%28cropped%29.jpg",
      "width": 245,
      "height": 320
    },
    "extract": "Serge David Gnabry [sɛʁʒ ɲabʁi] ist ein deutscher Fußballspieler. Er wechselte bereits im Jugendalter nach England und spielt seit 2016 in der Bundesliga. 2016 gewann der vielfache Junioren-Nationalspieler mit der Olympia-Auswahl bei den Olympischen Spielen in Brasilien die Silbermedaille und kam im selben Jahr zu ersten Einsätzen für die deutsche Nationalmannschaft. Seit Juli 2017 steht er beim FC Bayern München unter Vertrag, mit dem er 2020 das „Sextuple“ aus Deutscher Meisterschaft, DFB-Pokal, UEFA Champions League, UEFA Super Cup, DFL-Supercup und FIFA-Klub-Weltmeisterschaft gewann.",
    "year": 1995,
    "month": 7,
    "day": 14
  },
  {
    "name": "John McPhee (Rennfahrer)",
    "birthday": "1994-7-14",
    "thumbnail": {
      "source": "https://upload.wikimedia.org/wikipedia/commons/thumb/f/fc/John_McPhee_2019.jpg/320px-John_McPhee_2019.jpg",
      "width": 320,
      "height": 270
    },
    "extract": "John McPhee ist ein britischer Motorradrennfahrer. Er startet seit 2010 in der 125-cm³- bzw. Moto3-Klasse der Motorrad-Weltmeisterschaft. Sein Spitzname lautet John McFast.",
    "year": 1994,
    "month": 7,
    "day": 14
  },
  {
    "name": "Amelia Pietrangelo",
    "birthday": "1993-7-14",
    "thumbnail": {
      "source": "https://upload.wikimedia.org/wikipedia/commons/thumb/0/0a/Amelia_Piet.jpg/254px-Amelia_Piet.jpg",
      "width": 254,
      "height": 320
    },
    "extract": "Amelia Pietrangelo ist eine kanadische Fußballspielerin.",
    "year": 1993,
    "month": 7,
    "day": 14
  },
  {
    "name": "Jonas Hofmann (Fußballspieler, 1992)",
    "birthday": "1992-7-14",
    "thumbnail": {
      "source": "https://upload.wikimedia.org/wikipedia/commons/thumb/b/b6/Jonas_Hofmann_2013_in_Wilhelmshaven.jpeg/183px-Jonas_Hofmann_2013_in_Wilhelmshaven.jpeg",
      "width": 183,
      "height": 320
    },
    "extract": "Jonas Hofmann ist ein deutscher Fußballspieler. Der Mittelfeldspieler steht bei Borussia Mönchengladbach unter Vertrag und ist Nationalspieler.",
    "year": 1992,
    "month": 7,
    "day": 14
  },
  {
    "name": "Jan Alexandrowitsch Nepomnjaschtschi",
    "birthday": "1990-7-14",
    "thumbnail": {
      "source": "https://upload.wikimedia.org/wikipedia/commons/thumb/4/41/Ian_Nepomniachtchi_Tal_Memorial_2018.jpg/243px-Ian_Nepomniachtchi_Tal_Memorial_2018.jpg",
      "width": 243,
      "height": 320
    },
    "extract": "Jan Alexandrowitsch Nepomnjaschtschi ist ein russischer Schachspieler. Er ist seit 2007 Großmeister. Bei der Schachweltmeisterschaft 2021 war er der Herausforderer von Weltmeister Magnus Carlsen.",
    "year": 1990,
    "month": 7,
    "day": 14
  },
  {
    "name": "Jessica Wich",
    "birthday": "1990-7-14",
    "thumbnail": {
      "source": "https://upload.wikimedia.org/wikipedia/commons/thumb/a/a8/Jessica_Wich.jpg/240px-Jessica_Wich.jpg",
      "width": 240,
      "height": 320
    },
    "extract": "Jessica Wich ist eine deutsche Fußballspielerin. Die Stürmerin steht seit der Saison 2014/15 beim Bundesligisten Bayer 04 Leverkusen unter Vertrag.",
    "year": 1990,
    "month": 7,
    "day": 14
  },
  {
    "name": "Sean Flynn (Schauspieler)",
    "birthday": "1989-7-14",
    "thumbnail": {
      "source": "https://upload.wikimedia.org/wikipedia/commons/thumb/0/03/Sean_Flynn_en_el_2020.jpg/221px-Sean_Flynn_en_el_2020.jpg",
      "width": 221,
      "height": 320
    },
    "extract": "Sean Flynn ist ein US-amerikanischer Schauspieler.",
    "year": 1989,
    "month": 7,
    "day": 14
  },
  {
    "name": "Conor McGregor",
    "birthday": "1988-7-14",
    "thumbnail": {
      "source": "https://upload.wikimedia.org/wikipedia/commons/thumb/4/4d/Conor_McGregor_2018.jpg/278px-Conor_McGregor_2018.jpg",
      "width": 278,
      "height": 320
    },
    "extract": "Conor Anthony McGregor ist ein irischer Mixed-Martial-Arts-Kämpfer bei der UFC. Er ist ehemaliger UFC Lightweight Champion und UFC Featherweight Champion sowie ehemaliger Cage Warriors Featherweight und Lightweight Champion.",
    "year": 1988,
    "month": 7,
    "day": 14
  },
  {
    "name": "Olli Muotka",
    "birthday": "1988-7-14",
    "thumbnail": {
      "source": "https://upload.wikimedia.org/wikipedia/commons/thumb/f/f3/Muotka_Olli.jpg/226px-Muotka_Olli.jpg",
      "width": 226,
      "height": 320
    },
    "extract": "Olli Muotka ist ein finnischer Skispringer.",
    "year": 1988,
    "month": 7,
    "day": 14
  },
  {
    "name": "Rhys Williams (Fußballspieler, 1988)",
    "birthday": "1988-7-14",
    "thumbnail": {
      "source": "https://upload.wikimedia.org/wikipedia/commons/thumb/6/63/Rhys_Williams.jpg/211px-Rhys_Williams.jpg",
      "width": 211,
      "height": 320
    },
    "extract": "Rhys Anthony Williams ist ein australisch-walisischer Fußballspieler.",
    "year": 1988,
    "month": 7,
    "day": 14
  },
  {
    "name": "Sara Canning",
    "birthday": "1987-7-14",
    "thumbnail": {
      "source": "https://upload.wikimedia.org/wikipedia/commons/thumb/b/b4/Sara_Canning.jpg/179px-Sara_Canning.jpg",
      "width": 179,
      "height": 320
    },
    "extract": "Sara Canning ist eine kanadische Schauspielerin.",
    "year": 1987,
    "month": 7,
    "day": 14
  },
  {
    "name": "Adam Johnson (Fußballspieler)",
    "birthday": "1987-7-14",
    "thumbnail": {
      "source": "https://upload.wikimedia.org/wikipedia/commons/thumb/6/66/Adam_Johnson_-_closeup.jpg/201px-Adam_Johnson_-_closeup.jpg",
      "width": 201,
      "height": 320
    },
    "extract": "Adam Johnson ist ein englischer Fußballspieler. Der zwölffache englische Nationalspieler ging aus der Jugendabteilung des FC Middlesbrough hervor und gewann mit Manchester City die englische Meisterschaft (2012) sowie den FA Cup (2011). Zuletzt stand der Mittelfeldspieler, der 265 Erstligapartien bestritt, beim AFC Sunderland unter Vertrag.",
    "year": 1987,
    "month": 7,
    "day": 14
  },
  {
    "name": "Ryan Sweeting",
    "birthday": "1987-7-14",
    "thumbnail": {
      "source": "https://upload.wikimedia.org/wikipedia/commons/thumb/6/68/Ryan_Sweeting_at_the_2010_US_Open_01.jpg/320px-Ryan_Sweeting_at_the_2010_US_Open_01.jpg",
      "width": 320,
      "height": 313
    },
    "extract": "Ryan Sweeting ist ein ehemaliger US-amerikanischer Tennisspieler.",
    "year": 1987,
    "month": 7,
    "day": 14
  },
  {
    "name": "Dan Smith (Sänger)",
    "birthday": "1986-7-14",
    "thumbnail": {
      "source": "https://upload.wikimedia.org/wikipedia/commons/thumb/f/f1/Bastille%2C_Rock_en_Seine_2016%2C_Paris_%2829311148711%29.jpg/320px-Bastille%2C_Rock_en_Seine_2016%2C_Paris_%2829311148711%29.jpg",
      "width": 320,
      "height": 240
    },
    "extract": "Daniel Campbell „Dan“ Smith ist ein englischer Singer-Songwriter. Er ist Leadsänger, Produzent, Songwriter und Gründer der Indie-Rock-Band Bastille. Die 2010 gegründete Band wurde 2013 mit dem Song „Pompeii“ bekannt. Zudem ist Dan Smith einer von drei Gründern des Record Labels „Best Laid Plans“.",
    "year": 1986,
    "month": 7,
    "day": 14
  },
  {
    "name": "Dennis Endras",
    "birthday": "1985-7-14",
    "thumbnail": {
      "source": "https://upload.wikimedia.org/wikipedia/commons/thumb/7/7a/2022-04-28_Eisb%C3%A4ren_Berlin_gegen_Adler_Mannheim_%28Deutsche_Eishockey-Liga_2021-22%2C_Playoff-Halbfinale%29_by_Sandro_Halank%E2%80%93069.jpg/213px-2022-04-28_Eisb%C3%A4ren_Berlin_gegen_Adler_Mannheim_%28Deutsche_Eishockey-Liga_2021-22%2C_Playoff-Halbfinale%29_by_Sandro_Halank%E2%80%93069.jpg",
      "width": 213,
      "height": 320
    },
    "extract": "Dennis Endras ist ein deutscher Eishockeytorwart, der seit der Saison 2022/2023 erneut für die Augsburger Panther aus der DEL spielt. Darüber hinaus war er Torwart der deutschen Eishockeynationalmannschaft.",
    "year": 1985,
    "month": 7,
    "day": 14
  },
  {
    "name": "Darrelle Revis",
    "birthday": "1985-7-14",
    "thumbnail": {
      "source": "https://upload.wikimedia.org/wikipedia/commons/thumb/4/45/Darrelle_Revis_ESPNWeekend2010-051.jpg/294px-Darrelle_Revis_ESPNWeekend2010-051.jpg",
      "width": 294,
      "height": 320
    },
    "extract": "Darrelle Shavar Revis ist ein ehemaliger US-amerikanischer American-Football-Spieler auf der Position des Cornerbacks. Er spielte für die New York Jets, die Tampa Bay Buccaneers, die New England Patriots und die Kansas City Chiefs insgesamt elf Jahre in der National Football League (NFL) – acht davon für die Jets. Mit den Patriots gewann er den Super Bowl XLIX.",
    "year": 1985,
    "month": 7,
    "day": 14
  },
  {
    "name": "Janko Božović",
    "birthday": "1985-7-14",
    "thumbnail": {
      "source": "https://upload.wikimedia.org/wikipedia/commons/thumb/5/5a/20150106_2037_Handball_AUTSUI_7796.jpg/213px-20150106_2037_Handball_AUTSUI_7796.jpg",
      "width": 213,
      "height": 320
    },
    "extract": "Janko Božović ist ein aus Jugoslawien stammender Handballspieler mit österreichischer Staatsbürgerschaft.",
    "year": 1985,
    "month": 7,
    "day": 14
  },
  {
    "name": "Samir Handanovič",
    "birthday": "1984-7-14",
    "thumbnail": {
      "source": "https://upload.wikimedia.org/wikipedia/commons/thumb/2/29/Samir_Handanovi%C4%87_Slovenia.jpg/207px-Samir_Handanovi%C4%87_Slovenia.jpg",
      "width": 207,
      "height": 320
    },
    "extract": "Samir Handanovič ist ein slowenischer Fußballtorwart. Er spielt seit Juli 2012 für Inter Mailand in der Serie A und absolvierte von 2004 bis 2015 insgesamt 81 Länderspiele für die slowenische Nationalmannschaft.",
    "year": 1984,
    "month": 7,
    "day": 14
  },
  {
    "name": "Igor Walerjewitsch Andrejew",
    "birthday": "1983-7-14",
    "thumbnail": {
      "source": "https://upload.wikimedia.org/wikipedia/commons/thumb/5/57/Andreev_WM13-003_%289482780463%29.jpg/209px-Andreev_WM13-003_%289482780463%29.jpg",
      "width": 209,
      "height": 320
    },
    "extract": "Igor Walerjewitsch Andrejew ist ein ehemaliger russischer Tennisspieler. Seit 2018 ist er Kapitän des Fed-Cup-Teams der Russian Tennis Federation.",
    "year": 1983,
    "month": 7,
    "day": 14
  },
  {
    "name": "Richard Heistand",
    "birthday": "1983-7-14",
    "thumbnail": {
      "source": "https://upload.wikimedia.org/wikipedia/commons/thumb/c/c4/FIA_Porsche_Supercup_Austria_2018_Nr._16_Heistand.jpg/320px-FIA_Porsche_Supercup_Austria_2018_Nr._16_Heistand.jpg",
      "width": 320,
      "height": 240
    },
    "extract": "Richard Heistand ist ein US-amerikanischer Autorennfahrer.",
    "year": 1983,
    "month": 7,
    "day": 14
  },
  {
    "name": "Primož Prošt",
    "birthday": "1983-7-14",
    "thumbnail": {
      "source": "https://upload.wikimedia.org/wikipedia/commons/thumb/b/be/Primo%C5%BE_Pro%C5%A1t_2013.jpg/230px-Primo%C5%BE_Pro%C5%A1t_2013.jpg",
      "width": 230,
      "height": 320
    },
    "extract": "Primož Prošt ist ein slowenischer Handballspieler.",
    "year": 1983,
    "month": 7,
    "day": 14
  },
  {
    "name": "Witalij Schumbarez",
    "birthday": "1983-7-14",
    "thumbnail": {
      "source": "https://upload.wikimedia.org/wikipedia/commons/thumb/2/2d/Adams_Bulls_Eye_-_Vitaliy_Schumbarets.jpg/320px-Adams_Bulls_Eye_-_Vitaliy_Schumbarets.jpg",
      "width": 320,
      "height": 194
    },
    "extract": "Witalij Ihorowytsch Schumbarez ist ein ehemaliger ukrainischer Skispringer.",
    "year": 1983,
    "month": 7,
    "day": 14
  },
  {
    "name": "Milow (Sänger)",
    "birthday": "1981-7-14",
    "thumbnail": {
      "source": "https://upload.wikimedia.org/wikipedia/commons/thumb/f/fc/Milow-2016.jpg/320px-Milow-2016.jpg",
      "width": 320,
      "height": 181
    },
    "extract": "Milow ist ein belgischer Singer-Songwriter, der mit englischsprachigen Titeln und Alben international erfolgreich ist.",
    "year": 1981,
    "month": 7,
    "day": 14
  },
  {
    "name": "Matti Hautamäki",
    "birthday": "1981-7-14",
    "thumbnail": {
      "source": "https://upload.wikimedia.org/wikipedia/commons/thumb/f/fc/Matti_Hautam%C3%A4ki_%282011%29.jpg/236px-Matti_Hautam%C3%A4ki_%282011%29.jpg",
      "width": 236,
      "height": 320
    },
    "extract": "Matti Antero Hautamäki ist ein ehemaliger finnischer Skispringer. Er ist der mittlere von drei Brüdern und der jüngere Bruder des ehemaligen Skispringers Jussi Hautamäki. Wie auch sein Bruder startete er für den Verein Puijon Hiihtoseura in Kuopio.",
    "year": 1981,
    "month": 7,
    "day": 14
  },
  {
    "name": "Potito Starace",
    "birthday": "1981-7-14",
    "thumbnail": {
      "source": "https://upload.wikimedia.org/wikipedia/commons/thumb/2/26/Starace_RG13_%289404553998%29.jpg/227px-Starace_RG13_%289404553998%29.jpg",
      "width": 227,
      "height": 320
    },
    "extract": "Potito Starace ist ein ehemaliger italienischer Tennisspieler.",
    "year": 1981,
    "month": 7,
    "day": 14
  },
  {
    "name": "Balian Buschbaum",
    "birthday": "1980-7-14",
    "thumbnail": {
      "source": "https://upload.wikimedia.org/wikipedia/commons/thumb/9/98/Balian_Buschbaum.jpg/282px-Balian_Buschbaum.jpg",
      "width": 282,
      "height": 320
    },
    "extract": "Balian Buschbaum war unter seinem Geburtsnamen Yvonne Buschbaum in der deutschen Leichtathletik im Stabhochsprung erfolgreich und beendete die Sportlerlaufbahn im November 2007.",
    "year": 1980,
    "month": 7,
    "day": 14
  },
  {
    "name": "Thorsten Hohmann",
    "birthday": "1979-7-14",
    "thumbnail": {
      "source": "https://upload.wikimedia.org/wikipedia/commons/thumb/4/40/Thorsten_Hohmann.JPG/320px-Thorsten_Hohmann.JPG",
      "width": 320,
      "height": 206
    },
    "extract": "Thorsten Hohmann ist ein deutscher Poolbillardspieler.",
    "year": 1979,
    "month": 7,
    "day": 14
  },
  {
    "name": "Robin Szolkowy",
    "birthday": "1979-7-14",
    "thumbnail": {
      "source": "https://upload.wikimedia.org/wikipedia/commons/thumb/5/5b/Aliona_Savchenko_%26_Robin_Szolkowy_2009_Europeans.jpg/224px-Aliona_Savchenko_%26_Robin_Szolkowy_2009_Europeans.jpg",
      "width": 224,
      "height": 320
    },
    "extract": " Robin Szolkowy [ʃɔlˈkoːviː] ist ein ehemaliger deutscher Eiskunstläufer im Paarlauf und jetziger Trainer und Sportfunktionär. Mit seiner Eiskunstlaufpartnerin Aljona Savchenko wurde er fünfmal Welt- und viermal Europameister.",
    "year": 1979,
    "month": 7,
    "day": 14
  },
  {
    "name": "Axel Teichmann",
    "birthday": "1979-7-14",
    "thumbnail": {
      "source": "https://upload.wikimedia.org/wikipedia/commons/thumb/d/da/TEICHMANN_Axel_Tour_de_Ski_2010.jpg/320px-TEICHMANN_Axel_Tour_de_Ski_2010.jpg",
      "width": 320,
      "height": 296
    },
    "extract": "Axel Teichmann ist ein ehemaliger deutscher Skilangläufer und Sportsoldat der Bundeswehr. Als zweimaliger Weltmeister ist er der erfolgreichste deutsche Skilangläufer bei Nordischen Skiweltmeisterschaften.",
    "year": 1979,
    "month": 7,
    "day": 14
  },
  {
    "name": "Mattias Ekström",
    "birthday": "1978-7-14",
    "thumbnail": {
      "source": "https://upload.wikimedia.org/wikipedia/commons/thumb/4/46/World_RX_-_2018_-_RD1_Barcelona_%2826563808867%29.jpg/213px-World_RX_-_2018_-_RD1_Barcelona_%2826563808867%29.jpg",
      "width": 213,
      "height": 320
    },
    "extract": "Bengt Mattias Ekström ist ein schwedischer Automobilrennfahrer. Er ist der Sohn des in den 1990er Jahren aktiven Rallycross-Fahrers Bengt Ekström (1953–2022).",
    "year": 1978,
    "month": 7,
    "day": 14
  },
  {
    "name": "Peter Abelsson",
    "birthday": "1977-7-14",
    "thumbnail": {
      "source": "https://upload.wikimedia.org/wikipedia/commons/thumb/f/fa/Peter_Abelsson1.jpg/320px-Peter_Abelsson1.jpg",
      "width": 320,
      "height": 213
    },
    "extract": "Peter Abelsson ist ein ehemaliger schwedischer Fußballspieler. Der Abwehrspieler bestritt seine Laufbahn in Schweden und Norwegen.",
    "year": 1977,
    "month": 7,
    "day": 14
  },
  {
    "name": "Josh MacNevin",
    "birthday": "1977-7-14",
    "thumbnail": {
      "source": "https://upload.wikimedia.org/wikipedia/commons/thumb/e/e9/Josh_Macnevin_01.JPG/240px-Josh_Macnevin_01.JPG",
      "width": 240,
      "height": 320
    },
    "extract": "Josh MacNevin ist ein ehemaliger kanadischer Eishockeyspieler, der zuletzt für TPS Turku in der SM-liiga spielte.",
    "year": 1977,
    "month": 7,
    "day": 14
  },
  {
    "name": "Victoria von Schweden",
    "birthday": "1977-7-14",
    "thumbnail": {
      "source": "https://upload.wikimedia.org/wikipedia/commons/thumb/7/77/Crown_Princess_Victoria_June_8%2C_2013_%28cropped%29.jpg/167px-Crown_Princess_Victoria_June_8%2C_2013_%28cropped%29.jpg",
      "width": 167,
      "height": 320
    },
    "extract": "Victoria Ingrid Alice Désirée, Kronprinzessin von Schweden, Herzogin von Västergötland ist als ältestes Kind von König Carl XVI. Gustaf und Königin Silvia die Kronprinzessin des Königreiches Schweden aus dem Hause Bernadotte.",
    "year": 1977,
    "month": 7,
    "day": 14
  },
  {
    "name": "Monique Covet",
    "birthday": "1976-7-14",
    "thumbnail": {
      "source": "https://upload.wikimedia.org/wikipedia/commons/4/45/Monique_Covet_cropped.jpg",
      "width": 288,
      "height": 300
    },
    "extract": "Monique Covet ist eine ungarische Pornodarstellerin. Sie ist seit 1995 als Darstellerin in der Porno-Branche tätig. Ihr ursprünglicher Familienname lautet Monika Visi. Der im Internet oftmals alternativ angegebene Nachname Cancellieri, ist ein Aliasname der von der Produktionsfirma Private in den ersten Jahren ihrer Karriere für sie verwendet wurde. Ihr Familienname wurde auf ihren Wunsch in den 2000er Jahren von der dafür zuständigen ungarischen Behörde abgeändert, da sie sich mit ihrer engeren Familie überworfen hatte, und ihren ursprünglichen Familiennamen nicht mehr tragen wollte.",
    "year": 1976,
    "month": 7,
    "day": 14
  },
  {
    "name": "Teddy Afro",
    "birthday": "1976-7-14",
    "thumbnail": {
      "source": "https://upload.wikimedia.org/wikipedia/commons/thumb/f/f8/Teddy_Afro.jpg/271px-Teddy_Afro.jpg",
      "width": 271,
      "height": 320
    },
    "extract": "Teddy Afro ist ein äthiopischer Sänger.",
    "year": 1976,
    "month": 7,
    "day": 14
  },
  {
    "name": "Amy Acuff",
    "birthday": "1975-7-14",
    "thumbnail": {
      "source": "https://upload.wikimedia.org/wikipedia/commons/thumb/4/42/Amy_Acuff_Valence_2008.jpg/320px-Amy_Acuff_Valence_2008.jpg",
      "width": 320,
      "height": 314
    },
    "extract": "Amy Acuff ist eine ehemalige US-amerikanische Hochspringerin.",
    "year": 1975,
    "month": 7,
    "day": 14
  },
  {
    "name": "Taboo (Rapper)",
    "birthday": "1975-7-14",
    "thumbnail": {
      "source": "https://upload.wikimedia.org/wikipedia/commons/thumb/9/90/Taboo_%28rapper%29_cropped.JPG/224px-Taboo_%28rapper%29_cropped.JPG",
      "width": 224,
      "height": 320
    },
    "extract": "Jaime Luis Gomez, besser bekannt als Taboo, ist ein US-amerikanischer Rapper mit mexikanisch-amerikanischer/nordamerikanischer Indianer-Abstammung. Er wurde mit der Hip-Hop-Gruppe The Black Eyed Peas bekannt.",
    "year": 1975,
    "month": 7,
    "day": 14
  },
  {
    "name": "Martina Hill",
    "birthday": "1974-7-14",
    "thumbnail": {
      "source": "https://upload.wikimedia.org/wikipedia/commons/thumb/d/de/2019-01-31-Martina_Hill-DFP_2019-4492_%28cropped%29.jpg/214px-2019-01-31-Martina_Hill-DFP_2019-4492_%28cropped%29.jpg",
      "width": 214,
      "height": 320
    },
    "extract": "Martina Hill ist eine deutsche Schauspielerin, Komikerin und Synchronsprecherin.",
    "year": 1974,
    "month": 7,
    "day": 14
  },
  {
    "name": "Andri Snær Magnason",
    "birthday": "1973-7-14",
    "thumbnail": {
      "source": "https://upload.wikimedia.org/wikipedia/commons/thumb/b/be/Andri_Snaer_Magnason.JPG/258px-Andri_Snaer_Magnason.JPG",
      "width": 258,
      "height": 320
    },
    "extract": "Andri Snær Magnason ist ein isländischer Schriftsteller. Er war ein Kandidat in der Präsidentschaftswahl in Island 2016.",
    "year": 1973,
    "month": 7,
    "day": 14
  },
  {
    "name": "Candela Peña",
    "birthday": "1973-7-14",
    "thumbnail": {
      "source": "https://upload.wikimedia.org/wikipedia/commons/thumb/9/99/Candela_Pe%C3%B1a_at_Premios_Goya_2017.jpg/320px-Candela_Pe%C3%B1a_at_Premios_Goya_2017.jpg",
      "width": 320,
      "height": 213
    },
    "extract": "Candela Peña ist eine spanische Schauspielerin.",
    "year": 1973,
    "month": 7,
    "day": 14
  },
  {
    "name": "Aron Kristjánsson",
    "birthday": "1972-7-14",
    "thumbnail": {
      "source": "https://upload.wikimedia.org/wikipedia/commons/thumb/8/88/Aron_Kristjansson_20171202.jpg/231px-Aron_Kristjansson_20171202.jpg",
      "width": 231,
      "height": 320
    },
    "extract": "Aron Kristjánsson ist ein isländischer Handballtrainer und ein ehemaliger Handballspieler.",
    "year": 1972,
    "month": 7,
    "day": 14
  },
  {
    "name": "Andreas Urs Sommer",
    "birthday": "1972-7-14",
    "thumbnail": {
      "source": "https://upload.wikimedia.org/wikipedia/commons/thumb/9/9f/AndreasUrsSommer_Fribourg_2012.JPG/214px-AndreasUrsSommer_Fribourg_2012.JPG",
      "width": 214,
      "height": 320
    },
    "extract": "Andreas Urs Sommer ist ein Schweizer Philosoph, Publizist und Numismatiker. Seit Oktober 2016 ist er Inhaber einer Akademie-Professur für Philosophie mit Schwerpunkt Kulturphilosophie und seit 2019 Geschäftsführender Direktor des Nietzsche-Forschungszentrums an der Albert-Ludwigs-Universität Freiburg.",
    "year": 1972,
    "month": 7,
    "day": 14
  },
  {
    "name": "Ross Rebagliati",
    "birthday": "1971-7-14",
    "thumbnail": {
      "source": "https://upload.wikimedia.org/wikipedia/commons/thumb/0/02/Rachael_Ashe_Photo_-_Coffee_with_Ross_Rebagliati_-_8.JPG/289px-Rachael_Ashe_Photo_-_Coffee_with_Ross_Rebagliati_-_8.JPG",
      "width": 289,
      "height": 320
    },
    "extract": "Ross Rebagliati ist ein kanadischer Unternehmer, Aktivist für die Cannabislegalisierung und ehemaliger professioneller Snowboarder. 1998 wurde er Riesenslalom-Olympiasieger; dabei sorgte er vor allem durch seine vorübergehende Disqualifikation wegen der Verwendung von Cannabis für internationale Schlagzeilen. Er führt ein Unternehmen, das cannabidiolhaltigen Arznei- und Lebensmittel herstellt und vertreibt.",
    "year": 1971,
    "month": 7,
    "day": 14
  },
  {
    "name": "Howard Webb",
    "birthday": "1971-7-14",
    "thumbnail": {
      "source": "https://upload.wikimedia.org/wikipedia/commons/thumb/f/fa/Howard_Webb_march11.jpg/211px-Howard_Webb_march11.jpg",
      "width": 211,
      "height": 320
    },
    "extract": "Howard Melton Webb, MBE ist ein ehemaliger englischer Fußballschiedsrichter.",
    "year": 1971,
    "month": 7,
    "day": 14
  },
  {
    "name": "Jeff Jarrett",
    "birthday": "1967-7-14",
    "thumbnail": {
      "source": "https://upload.wikimedia.org/wikipedia/commons/thumb/1/10/Jeff_Jarrett_at_a_GFW_show_in_June_2015.jpg/216px-Jeff_Jarrett_at_a_GFW_show_in_June_2015.jpg",
      "width": 216,
      "height": 320
    },
    "extract": "Jeffrey Leonard Jarrett, besser bekannt unter seinem Ringnamen Jeff Jarrett ist ein US-amerikanischer Wrestler. Jarrett trat für alle großen Wrestlingligen Nordamerikas auf. Seine bisher größten Erfolge waren der sechsfache Gewinn des NWA World Heavyweight Champion Titels, der vierfache Gewinn des WCW World Heavyweight Champion Titels, sowie der vierfache Gewinn des WWF Intercontinental Champion Titels.",
    "year": 1967,
    "month": 7,
    "day": 14
  },
  {
    "name": "Matthew Fox (Schauspieler)",
    "birthday": "1966-7-14",
    "thumbnail": {
      "source": "https://upload.wikimedia.org/wikipedia/commons/thumb/2/27/MatthewFox.png/144px-MatthewFox.png",
      "width": 144,
      "height": 320
    },
    "extract": "Matthew Fox ist ein US-amerikanischer Schauspieler.",
    "year": 1966,
    "month": 7,
    "day": 14
  },
  {
    "name": "Ralf Waldmann",
    "birthday": "1966-7-14",
    "thumbnail": {
      "source": "https://upload.wikimedia.org/wikipedia/commons/thumb/a/a4/Ralf_Waldmann_1992_Japanese_GP.jpg/320px-Ralf_Waldmann_1992_Japanese_GP.jpg",
      "width": 320,
      "height": 247
    },
    "extract": "Ralf Waldmann war ein deutscher Motorradrennfahrer.",
    "year": 1966,
    "month": 7,
    "day": 14
  },
  {
    "name": "Thomas Aigner (Medienunternehmer)",
    "birthday": "1964-7-14",
    "thumbnail": {
      "source": "https://upload.wikimedia.org/wikipedia/commons/thumb/3/3b/PE_ThomasAigner_Portr%C3%A4t.jpg/256px-PE_ThomasAigner_Portr%C3%A4t.jpg",
      "width": 256,
      "height": 320
    },
    "extract": "Thomas „Thomy“ Aigner ist ein ehemaliger österreichischer Radio- und Fernsehmoderator sowie Journalist, der als Medienunternehmer und Dozent tätig ist.",
    "year": 1964,
    "month": 7,
    "day": 14
  },
  {
    "name": "Rolando Maran",
    "birthday": "1963-7-14",
    "thumbnail": {
      "source": "https://upload.wikimedia.org/wikipedia/commons/thumb/6/6a/Rolando_Maran.JPG/320px-Rolando_Maran.JPG",
      "width": 320,
      "height": 207
    },
    "extract": "Rolando Maran ist ein ehemaliger italienischer Fußballspieler und heutiger -trainer.",
    "year": 1963,
    "month": 7,
    "day": 14
  },
  {
    "name": "Kyle Gass",
    "birthday": "1960-7-14",
    "thumbnail": {
      "source": "https://upload.wikimedia.org/wikipedia/commons/thumb/f/f3/2017_Woodstock_203_Kyle_Gass_Band.jpg/213px-2017_Woodstock_203_Kyle_Gass_Band.jpg",
      "width": 213,
      "height": 320
    },
    "extract": "Kyle Gass ist ein US-amerikanischer Musiker und Schauspieler. Zusammen mit Jack Black bildet er die komödiantische Rockband Tenacious D, in deren Werken er oft die Spitznamen KG und Kage trägt. Gass spielt in der Band die Leadgitarre und singt im Hintergrund.",
    "year": 1960,
    "month": 7,
    "day": 14
  },
  {
    "name": "Jane Lynch",
    "birthday": "1960-7-14",
    "thumbnail": {
      "source": "https://upload.wikimedia.org/wikipedia/commons/thumb/a/a7/Jane_Lynch_Peabody_2010_%288266458405%29_%28cropped%29.jpg/238px-Jane_Lynch_Peabody_2010_%288266458405%29_%28cropped%29.jpg",
      "width": 238,
      "height": 320
    },
    "extract": "Jane Marie Lynch ist eine US-amerikanische Autorin, Schriftstellerin, Sängerin, Schauspielerin und Komikerin.",
    "year": 1960,
    "month": 7,
    "day": 14
  },
  {
    "name": "Jackie Earle Haley",
    "birthday": "1960-7-14",
    "thumbnail": {
      "source": "https://upload.wikimedia.org/wikipedia/commons/thumb/7/7c/Jackie_Earle_Haley_at_WonderCon_2010_2.JPG/320px-Jackie_Earle_Haley_at_WonderCon_2010_2.JPG",
      "width": 320,
      "height": 240
    },
    "extract": "Jackie Earle Haley ist ein US-amerikanischer Schauspieler und Filmregisseur.",
    "year": 1960,
    "month": 7,
    "day": 14
  },
  {
    "name": "Klaus Schreiber (Schauspieler)",
    "birthday": "1959-7-14",
    "thumbnail": {
      "source": "https://upload.wikimedia.org/wikipedia/commons/thumb/1/12/Klaus_Christian_Schreiber.jpg/320px-Klaus_Christian_Schreiber.jpg",
      "width": 320,
      "height": 213
    },
    "extract": "Klaus Christian Schreiber ist ein deutscher Schauspieler.",
    "year": 1959,
    "month": 7,
    "day": 14
  },
  {
    "name": "Mircea Geoană",
    "birthday": "1958-7-14",
    "thumbnail": {
      "source": "https://upload.wikimedia.org/wikipedia/commons/thumb/c/cd/Mircea_Geoana_01.jpg/286px-Mircea_Geoana_01.jpg",
      "width": 286,
      "height": 320
    },
    "extract": "Mircea Geoană ist ein Politiker in Rumänien und war bis 2004 Außenminister. Er gilt als gewandter Diplomat und konnte Ende 2004 die EU-Beitrittsverhandlungen erfolgreich abschließen.",
    "year": 1958,
    "month": 7,
    "day": 14
  },
  {
    "name": "Arthur Albiston",
    "birthday": "1957-7-14",
    "thumbnail": {
      "source": "https://upload.wikimedia.org/wikipedia/commons/e/eb/Albiston%2C_Arthur.jpg",
      "width": 300,
      "height": 200
    },
    "extract": "Arthur Richard Albiston ist ein schottischer Fußballspieler und Fußballtrainer.",
    "year": 1957,
    "month": 7,
    "day": 14
  },
  {
    "name": "Martha Coakley",
    "birthday": "1953-7-14",
    "thumbnail": {
      "source": "https://upload.wikimedia.org/wikipedia/commons/thumb/d/d4/Martha_Coakley_Suffolk_Feb2014.jpg/241px-Martha_Coakley_Suffolk_Feb2014.jpg",
      "width": 241,
      "height": 320
    },
    "extract": "Martha Mary Coakley ist eine US-amerikanische Juristin und Politikerin. Von 2007 bis 2015 war die Demokratin Attorney General und damit Mitglied der Regierung des Bundesstaates Massachusetts. Als Kandidatin ihrer Partei für den US-Senat 2010 und das Amt des Gouverneurs 2014 verlor sie jeweils gegen den republikanischen Bewerber.",
    "year": 1953,
    "month": 7,
    "day": 14
  },
  {
    "name": "Roland Jahn",
    "birthday": "1953-7-14",
    "thumbnail": {
      "source": "https://upload.wikimedia.org/wikipedia/commons/thumb/0/00/17-05-10-Pressetermin-Weissensee-RalfR_RR79303.jpg/230px-17-05-10-Pressetermin-Weissensee-RalfR_RR79303.jpg",
      "width": 230,
      "height": 320
    },
    "extract": "Roland Jahn ist ein deutscher Journalist. Er war der letzte Leiter der Stasiunterlagenbehörde BStU.",
    "year": 1953,
    "month": 7,
    "day": 14
  },
  {
    "name": "José Aristeu Vieira",
    "birthday": "1952-7-14",
    "thumbnail": {
      "source": "https://upload.wikimedia.org/wikipedia/commons/thumb/e/e4/Josearisteu.JPG/320px-Josearisteu.JPG",
      "width": 320,
      "height": 320
    },
    "extract": "José Aristeu Vieira ist ein brasilianischer Geistlicher und römisch-katholischer Bischof von Luz.",
    "year": 1952,
    "month": 7,
    "day": 14
  },
  {
    "name": "Werner E. Gerabek",
    "birthday": "1952-7-14",
    "thumbnail": {
      "source": "https://upload.wikimedia.org/wikipedia/commons/thumb/9/92/Werner_E._Gerabek.jpg/254px-Werner_E._Gerabek.jpg",
      "width": 254,
      "height": 320
    },
    "extract": "Werner Erwin Gerabek ist ein deutscher Historiker, Germanist und Medizinhistoriker sowie Gründer und Geschäftsführer des Deutschen Wissenschafts-Verlags (DWV).",
    "year": 1952,
    "month": 7,
    "day": 14
  },
  {
    "name": "Berhaneyesus Demerew Souraphiel",
    "birthday": "1948-7-14",
    "thumbnail": {
      "source": "https://upload.wikimedia.org/wikipedia/commons/thumb/3/32/Berhaneyesus_Demerew_Souraphiel_detail.jpg/195px-Berhaneyesus_Demerew_Souraphiel_detail.jpg",
      "width": 195,
      "height": 320
    },
    "extract": "Berhaneyesus Demerew Kardinal Souraphiel CM ist Erzbischof der Äthiopisch-katholischen Kirche in Addis Abeba und Metropolit der Kirchenprovinz Addis Abeba.",
    "year": 1948,
    "month": 7,
    "day": 14
  },
  {
    "name": "Goodwill Zwelithini kaBhekuzulu",
    "birthday": "1948-7-14",
    "thumbnail": {
      "source": "https://upload.wikimedia.org/wikipedia/commons/thumb/c/c9/King_Goodwill_Zwelithini.jpg/213px-King_Goodwill_Zwelithini.jpg",
      "width": 213,
      "height": 320
    },
    "extract": "Goodwill Zwelithini kaBhekuzulu war nach der südafrikanischen Verfassung König der Zulu.",
    "year": 1948,
    "month": 7,
    "day": 14
  },
  {
    "name": "James Saunders (Tänzer)",
    "birthday": "1946-7-14",
    "thumbnail": {
      "source": "https://upload.wikimedia.org/wikipedia/commons/thumb/9/9f/James_Saunders_K%C3%B6ln_01.jpg/255px-James_Saunders_K%C3%B6ln_01.jpg",
      "width": 255,
      "height": 320
    },
    "extract": "James Saunders war ein US-amerikanischer Tänzer, Choreograf und Bewegungslehrer.",
    "year": 1946,
    "month": 7,
    "day": 14
  },
  {
    "name": "Javier Solana",
    "birthday": "1942-7-14",
    "thumbnail": {
      "source": "https://upload.wikimedia.org/wikipedia/commons/thumb/f/f4/Javier_Solana_%282007%29.jpg/320px-Javier_Solana_%282007%29.jpg",
      "width": 320,
      "height": 240
    },
    "extract": "Javier Solana de Madariaga ist ein spanischer Politiker. Von 1995 bis 1999 war er Generalsekretär der NATO. Von 1999 bis Ende November 2009 war er Generalsekretär des Rates der Europäischen Union und Hoher Vertreter für die Gemeinsame Außen- und Sicherheitspolitik (GASP), ab 25. November 1999 darüber hinaus auch Generalsekretär der Westeuropäischen Union (WEU). Aufgrund seiner weitreichenden Kompetenzen in außen- und verteidigungstechnischen Fragen der EU wurde Solana häufig als deren „Außenminister“ bezeichnet.",
    "year": 1942,
    "month": 7,
    "day": 14
  },
  {
    "name": "Daniel Gache",
    "birthday": "1941-7-14",
    "thumbnail": {
      "source": "https://upload.wikimedia.org/wikipedia/commons/thumb/4/49/Chevron_B36_Mont-Tremblant.jpg/320px-Chevron_B36_Mont-Tremblant.jpg",
      "width": 320,
      "height": 240
    },
    "extract": "Daniel Gache ist ein ehemaliger französischer Autorennfahrer.",
    "year": 1941,
    "month": 7,
    "day": 14
  },
  {
    "name": "Andreas Khol",
    "birthday": "1941-7-14",
    "thumbnail": {
      "source": "https://upload.wikimedia.org/wikipedia/commons/thumb/0/05/Andreas_Khol_September_2006_%28cropped%29.jpg/258px-Andreas_Khol_September_2006_%28cropped%29.jpg",
      "width": 258,
      "height": 320
    },
    "extract": "Andreas Khol ist ein ehemaliger österreichischer Politiker der ÖVP. Von 2002 bis 2006 war er Präsident des österreichischen Nationalrates. Er trat als Kandidat für die Bundespräsidentenwahl in Österreich 2016 an.",
    "year": 1941,
    "month": 7,
    "day": 14
  },
  {
    "name": "Kwame Addo-Kufuor",
    "birthday": "1940-7-14",
    "thumbnail": {
      "source": "https://upload.wikimedia.org/wikipedia/commons/thumb/6/63/DR.KWAME_ADDO_KUFOUR.jpg/240px-DR.KWAME_ADDO_KUFOUR.jpg",
      "width": 240,
      "height": 320
    },
    "extract": "Kwame Addo-Kufuor ist ein ghanaischer Politiker aus der Region Ashanti. Er war bis zum 31. Juli 2007 Verteidigungsminister in Ghana, Mitglied des ghanaischen Parlaments für den Wahlkreis Manhyia und ist der Bruder von Präsident John Agyekum Kufuor.",
    "year": 1940,
    "month": 7,
    "day": 14
  },
  {
    "name": "Karel Gott",
    "birthday": "1939-7-14",
    "thumbnail": {
      "source": "https://upload.wikimedia.org/wikipedia/commons/thumb/c/ce/Karel_Gott_2018.jpg/242px-Karel_Gott_2018.jpg",
      "width": 242,
      "height": 320
    },
    "extract": "Karel Gott war ein tschechischer Sänger, Komponist und Maler. Der in Deutschland als „goldene Stimme aus Prag“ berühmt gewordene Schlagersänger, der auch auf Deutsch sang, hat Schätzungen zufolge mehr als 50 Millionen Tonträger verkauft.",
    "year": 1939,
    "month": 7,
    "day": 14
  },
  {
    "name": "Günther Jansen (Politiker, 1936)",
    "birthday": "1936-7-14",
    "thumbnail": {
      "source": "https://upload.wikimedia.org/wikipedia/commons/thumb/7/7c/Demonstration_des_Deutschen_Gewerkschaftsbundes_%28DGB%29_gegen_die_geplante_Ver%C3%A4nderung_des_%C2%A7_116_des_Arbeitsf%C3%B6rderungsgesetzes_%28AFG%29_%28Kiel_75.083%29.jpg/217px-Demonstration_des_Deutschen_Gewerkschaftsbundes_%28DGB%29_gegen_die_geplante_Ver%C3%A4nderung_des_%C2%A7_116_des_Arbeitsf%C3%B6rderungsgesetzes_%28AFG%29_%28Kiel_75.083%29.jpg",
      "width": 217,
      "height": 320
    },
    "extract": "Günther Jansen ist ein deutscher Politiker der SPD.",
    "year": 1936,
    "month": 7,
    "day": 14
  },
  {
    "name": "Ei-ichi Negishi",
    "birthday": "1935-7-14",
    "thumbnail": {
      "source": "https://upload.wikimedia.org/wikipedia/commons/thumb/8/8c/Nobel_Prize_2010-Press_Conference_KVA-DSC_7398.jpg/240px-Nobel_Prize_2010-Press_Conference_KVA-DSC_7398.jpg",
      "width": 240,
      "height": 320
    },
    "extract": "Ei-ichi Negishi war ein japanischer Chemiker. Für die Negishi-Kupplung erhielt er 2010 gemeinsam mit Richard F. Heck und Akira Suzuki den Nobelpreis für Chemie.",
    "year": 1935,
    "month": 7,
    "day": 14
  },
  {
    "name": "Marcel Gotlieb",
    "birthday": "1934-7-14",
    "thumbnail": {
      "source": "https://upload.wikimedia.org/wikipedia/commons/thumb/b/b9/Marcel_Gotlib_2011_a.jpg/240px-Marcel_Gotlib_2011_a.jpg",
      "width": 240,
      "height": 320
    },
    "extract": "Marcel Gotlieb, bekannt als Gotlib, war ein französischer Comiczeichner.",
    "year": 1934,
    "month": 7,
    "day": 14
  },
  {
    "name": "Dragoljub Mićunović",
    "birthday": "1930-7-14",
    "thumbnail": {
      "source": "https://upload.wikimedia.org/wikipedia/commons/thumb/4/4e/Dragoljub_Micunovic.jpg/320px-Dragoljub_Micunovic.jpg",
      "width": 320,
      "height": 214
    },
    "extract": "Dragoljub Mićunović war Professor für Philosophie an der Universität Belgrad und Vorsitzender der Demokratska Stranka in Serbien.",
    "year": 1930,
    "month": 7,
    "day": 14
  },
  {
    "name": "Martin Accola",
    "birthday": "1928-7-14",
    "thumbnail": {
      "source": "https://upload.wikimedia.org/wikipedia/commons/thumb/0/0d/Kanzel_Kirche_Flims.jpg/240px-Kanzel_Kirche_Flims.jpg",
      "width": 240,
      "height": 320
    },
    "extract": "Martin Accola war ein reformierter Pfarrer im Kanton Graubünden und 10 Jahre Dekan der evangelisch-reformierten Kirche des Kantons Graubünden.",
    "year": 1928,
    "month": 7,
    "day": 14
  },
  {
    "name": "Harry Dean Stanton",
    "birthday": "1926-7-14",
    "thumbnail": {
      "source": "https://upload.wikimedia.org/wikipedia/commons/thumb/2/27/HarryDeanStanton-1.jpg/227px-HarryDeanStanton-1.jpg",
      "width": 227,
      "height": 320
    },
    "extract": "Harry Dean Stanton war ein US-amerikanischer Schauspieler und Musiker. Er galt als einer der vielseitigsten Nebendarsteller des amerikanischen Films.",
    "year": 1926,
    "month": 7,
    "day": 14
  },
  {
    "name": "Francisco Álvarez Martínez",
    "birthday": "1925-7-14",
    "thumbnail": {
      "source": "https://upload.wikimedia.org/wikipedia/commons/thumb/0/03/Card._Alvarez_Martinez_%2830913897465%29.jpg/254px-Card._Alvarez_Martinez_%2830913897465%29.jpg",
      "width": 254,
      "height": 320
    },
    "extract": "Francisco Kardinal Álvarez Martínez war ein spanischer römisch-katholischer Geistlicher, Erzbischof von Toledo und Primas von Spanien.",
    "year": 1925,
    "month": 7,
    "day": 14
  },
  {
    "name": "René Favaloro",
    "birthday": "1923-7-14",
    "thumbnail": {
      "source": "https://upload.wikimedia.org/wikipedia/commons/thumb/f/f5/Rene_Favaloro.JPG/292px-Rene_Favaloro.JPG",
      "width": 292,
      "height": 320
    },
    "extract": "René Gerónimo Favaloro war ein Erfinder, Pädagoge und Herzchirurg, der dafür bekannt ist, 1967 einen Koronarbypass unter Verwendung der Vena saphena magna entwickelt zu haben.",
    "year": 1923,
    "month": 7,
    "day": 14
  },
  {
    "name": "Geoffrey Wilkinson",
    "birthday": "1921-7-14",
    "thumbnail": {
      "source": "https://upload.wikimedia.org/wikipedia/commons/thumb/1/1b/Geoffrey_Wilkinson_%28ca._1976%29.jpg/279px-Geoffrey_Wilkinson_%28ca._1976%29.jpg",
      "width": 279,
      "height": 320
    },
    "extract": "Sir Geoffrey Wilkinson war ein britischer Chemiker und Professor für Anorganische Chemie, der 1973 mit dem Nobelpreis für Chemie ausgezeichnet wurde. Wilkison gilt als Pionier der Metallorganischen Chemie und der homogenen Übergangsmetallkatalyse. Er entwickelte außerdem den Wilkinson-Katalysator, der für die katalytische Hydrierung von Alkenen mit molekularem Wasserstoff verwendet wird.",
    "year": 1921,
    "month": 7,
    "day": 14
  },
  {
    "name": "Lino Ventura",
    "birthday": "1919-7-14",
    "thumbnail": {
      "source": "https://upload.wikimedia.org/wikipedia/commons/thumb/a/aa/Lino_Ventura_%E2%80%94_Il_Re_di_Poggioreale.jpg/257px-Lino_Ventura_%E2%80%94_Il_Re_di_Poggioreale.jpg",
      "width": 257,
      "height": 320
    },
    "extract": "Lino Ventura war ein italienisch-französischer Filmschauspieler. Er zählte über Jahrzehnte zu den beliebtesten französischen Charakterdarstellern.",
    "year": 1919,
    "month": 7,
    "day": 14
  },
  {
    "name": "Ingmar Bergman",
    "birthday": "1918-7-14",
    "thumbnail": {
      "source": "https://upload.wikimedia.org/wikipedia/commons/thumb/f/f2/Ingmar_Bergman_%281966%29.jpg/239px-Ingmar_Bergman_%281966%29.jpg",
      "width": 239,
      "height": 320
    },
    "extract": " [ˌiŋːmaɾ ˈbæɾːʝman] war ein schwedischer Drehbuchautor, Film- und Theaterregisseur. Da er oft in seiner Entwicklung Theater und Film fast parallel bearbeitete, waren sowohl die Bühne als auch der Film wechselseitig Impulsgeber für das jeweils andere Medium. Im Jahre 1997 wurde Bergman bei den Filmfestspielen in Cannes als „Bester Filmregisseur aller Zeiten“ geehrt.",
    "year": 1918,
    "month": 7,
    "day": 14
  },
  {
    "name": "Arthur Laurents",
    "birthday": "1918-7-14",
    "thumbnail": {
      "source": "https://upload.wikimedia.org/wikipedia/commons/thumb/8/85/Arthur_laurents.JPG/240px-Arthur_laurents.JPG",
      "width": 240,
      "height": 320
    },
    "extract": "Arthur Laurents war ein US-amerikanischer Schriftsteller, Drehbuchautor und Theaterregisseur.",
    "year": 1918,
    "month": 7,
    "day": 14
  },
  {
    "name": "Natalia Ginzburg",
    "birthday": "1916-7-14",
    "thumbnail": {
      "source": "https://upload.wikimedia.org/wikipedia/commons/thumb/7/7e/Sandro_Pertini_e_Natalia_Ginzburg.jpg/320px-Sandro_Pertini_e_Natalia_Ginzburg.jpg",
      "width": 320,
      "height": 254
    },
    "extract": "Natalia Ginzburg war eine der bedeutendsten Schriftstellerinnen der italienischen Literatur des 20. Jahrhunderts.",
    "year": 1916,
    "month": 7,
    "day": 14
  },
  {
    "name": "Fritz Erler",
    "birthday": "1913-7-14",
    "thumbnail": {
      "source": "https://upload.wikimedia.org/wikipedia/commons/thumb/d/d8/McNamara_with_Erler_and_Brandt_at_Pentagon_1965.JPEG/320px-McNamara_with_Erler_and_Brandt_at_Pentagon_1965.JPEG",
      "width": 320,
      "height": 213
    },
    "extract": "Fritz Erler war ein deutscher SPD-Politiker. Er galt als Experte für Verteidigungsfragen und zeitweilig als möglicher Kanzlerkandidat der Partei.",
    "year": 1913,
    "month": 7,
    "day": 14
  },
  {
    "name": "Gerald Ford",
    "birthday": "1913-7-14",
    "thumbnail": {
      "source": "https://upload.wikimedia.org/wikipedia/commons/thumb/3/36/Gerald_Ford_presidential_portrait_%28cropped%29.jpg/257px-Gerald_Ford_presidential_portrait_%28cropped%29.jpg",
      "width": 257,
      "height": 320
    },
    "extract": "Gerald Rudolph Ford, Jr. war von 1974 bis 1977 der 38. Präsident der Vereinigten Staaten. Er war Mitglied der Republikanischen Partei und wurde 1965 Fraktionsvorsitzender seiner Partei im Repräsentantenhaus, dem er von 1949 bis 1973 angehörte.",
    "year": 1913,
    "month": 7,
    "day": 14
  },
  {
    "name": "Woody Guthrie",
    "birthday": "1912-7-14",
    "thumbnail": {
      "source": "https://upload.wikimedia.org/wikipedia/commons/thumb/e/e0/Woody_Guthrie_NYWTS.jpg/255px-Woody_Guthrie_NYWTS.jpg",
      "width": 255,
      "height": 320
    },
    "extract": "Woodrow Wilson Guthrie, bekannter unter seinem Spitz- und Künstlernamen „Woody“ Guthrie, war ein US-amerikanischer Singer-Songwriter. Der politisch im gewerkschaftsnahen linken Spektrum aktive Lyriker und Balladenverfasser beeinflusste maßgeblich die US-amerikanische Folkmusik.",
    "year": 1912,
    "month": 7,
    "day": 14
  },
  {
    "name": "Pawel Prudnikau",
    "birthday": "1911-7-14",
    "thumbnail": {
      "source": "https://upload.wikimedia.org/wikipedia/commons/thumb/8/8a/Pavel_Prudnikau.jpg/244px-Pavel_Prudnikau.jpg",
      "width": 244,
      "height": 320
    },
    "extract": "Pawel Iwanawitsch Prudnikau war ein weißrussischer Dichter und Schriftsteller.",
    "year": 1911,
    "month": 7,
    "day": 14
  },
  {
    "name": "Terry-Thomas",
    "birthday": "1911-7-14",
    "thumbnail": {
      "source": "https://upload.wikimedia.org/wikipedia/commons/thumb/e/e1/Premiere_van_de_film_Knotsgekke_kerels_in_hun_vliegende_kratten_%28Engelse_titel%2C_Bestanddeelnr_917-9689.jpg/320px-Premiere_van_de_film_Knotsgekke_kerels_in_hun_vliegende_kratten_%28Engelse_titel%2C_Bestanddeelnr_917-9689.jpg",
      "width": 320,
      "height": 211
    },
    "extract": "Terry-Thomas war ein englischer Schauspieler und Komiker.",
    "year": 1911,
    "month": 7,
    "day": 14
  },
  {
    "name": "Hermann Dietzfelbinger",
    "birthday": "1908-7-14",
    "thumbnail": {
      "source": "https://upload.wikimedia.org/wikipedia/commons/8/88/Hermann_Dietzfelbinger_%281965%29.jpg",
      "width": 183,
      "height": 243
    },
    "extract": "Hermann Dietzfelbinger war ein deutscher evangelischer Pfarrer, Theologe und bayerischer Landesbischof.",
    "year": 1908,
    "month": 7,
    "day": 14
  },
  {
    "name": "Pierre Angénieux",
    "birthday": "1907-7-14",
    "thumbnail": {
      "source": "https://upload.wikimedia.org/wikipedia/commons/thumb/6/69/Angenieuxlogoold.jpg/320px-Angenieuxlogoold.jpg",
      "width": 320,
      "height": 279
    },
    "extract": "Pierre Angénieux war ein französischer Mathematiker, Ingenieur und Unternehmer.",
    "year": 1907,
    "month": 7,
    "day": 14
  },
  {
    "name": "Annabella",
    "birthday": "1907-7-14",
    "thumbnail": {
      "source": "https://upload.wikimedia.org/wikipedia/commons/thumb/f/f0/Annabella_1934.jpg/236px-Annabella_1934.jpg",
      "width": 236,
      "height": 320
    },
    "extract": "Annabella, eigentlich Suzanne Georgette Charpentier, war eine französische Filmschauspielerin.",
    "year": 1907,
    "month": 7,
    "day": 14
  },
  {
    "name": "Olive Borden",
    "birthday": "1906-7-14",
    "thumbnail": {
      "source": "https://upload.wikimedia.org/wikipedia/commons/thumb/0/07/Olive_Borden_Stars_of_the_Photoplay.jpg/241px-Olive_Borden_Stars_of_the_Photoplay.jpg",
      "width": 241,
      "height": 320
    },
    "extract": "Olive Borden war eine US-amerikanische Schauspielerin in der Stummfilmzeit. Ihr Spitzname lautete The Joy Girl.",
    "year": 1906,
    "month": 7,
    "day": 14
  },
  {
    "name": "William H. Tunner",
    "birthday": "1906-7-14",
    "thumbnail": {
      "source": "https://upload.wikimedia.org/wikipedia/commons/thumb/2/27/William_H._Tunner.jpeg/259px-William_H._Tunner.jpeg",
      "width": 259,
      "height": 320
    },
    "extract": "William Henry Tunner war ein US-amerikanischer Generalleutnant der United States Army Air Forces (USAAF) bzw. deren Nachfolger US Air Force. Tunner zeichnete sich durch seine Leistungen bei der Einrichtung, Optimierung und Durchführung von globalen Logistiklösungen auf dem Luftweg aus, darunter der Hump-Luftbrücke zwischen Indien und China (1942–1945), der Berliner Luftbrücke (1948–1949) und der Luftbrücke im Koreakrieg (1951–1953).",
    "year": 1906,
    "month": 7,
    "day": 14
  },
  {
    "name": "Hans Bernd Gisevius",
    "birthday": "1904-7-14",
    "thumbnail": {
      "source": "https://upload.wikimedia.org/wikipedia/commons/8/80/Gisevius_2_460426_NARA.jpg",
      "width": 210,
      "height": 156
    },
    "extract": "Gustav-Adolf Timotheus Hans Bernd Gisevius war ein deutscher Politiker, Staatsbeamter und Widerstandskämpfer.",
    "year": 1904,
    "month": 7,
    "day": 14
  },
  {
    "name": "Odette Siko",
    "birthday": "1899-7-14",
    "thumbnail": {
      "source": "https://upload.wikimedia.org/wikipedia/commons/thumb/0/07/24_Heures_du_Mans_1930%2C_la_Bugatti_T40_de_Mmes_Mareuse_et_Siko%2C_septi%C3%A8mes.jpg/320px-24_Heures_du_Mans_1930%2C_la_Bugatti_T40_de_Mmes_Mareuse_et_Siko%2C_septi%C3%A8mes.jpg",
      "width": 320,
      "height": 256
    },
    "extract": "Odette Séguin, verheiratete Coville, bekannt als Odette Siko war eine französische Autorennfahrerin.",
    "year": 1899,
    "month": 7,
    "day": 14
  },
  {
    "name": "Happy Chandler",
    "birthday": "1898-7-14",
    "thumbnail": {
      "source": "https://upload.wikimedia.org/wikipedia/commons/thumb/4/44/Happy_Chandler_-_Harris_and_Ewing_Crop.jpg/232px-Happy_Chandler_-_Harris_and_Ewing_Crop.jpg",
      "width": 232,
      "height": 320
    },
    "extract": "Albert Benjamin „Happy“ Chandler war ein US-amerikanischer Politiker, Gouverneur und US-Senator für den Bundesstaat Kentucky und Sportfunktionär.",
    "year": 1898,
    "month": 7,
    "day": 14
  },
  {
    "name": "Otto Krone (Schauspieler)",
    "birthday": "1898-7-14",
    "thumbnail": {
      "source": "https://upload.wikimedia.org/wikipedia/commons/f/fd/Otto_Krone_%28actor%29-01.jpg",
      "width": 160,
      "height": 250
    },
    "extract": "Adolf Ernst Hans Werner Otto Krone war ein deutscher Schauspieler aus der DEFA-Zeit und Synchronsprecher.",
    "year": 1898,
    "month": 7,
    "day": 14
  },
  {
    "name": "Plaek Phibunsongkhram",
    "birthday": "1897-7-14",
    "thumbnail": {
      "source": "https://upload.wikimedia.org/wikipedia/commons/thumb/1/15/PPS_2.JPG/187px-PPS_2.JPG",
      "width": 187,
      "height": 320
    },
    "extract": "Plaek Phibunsongkhram war ein thailändischer Heeresoffizier und Politiker. Er war von 1938 bis 1944 und erneut von 1948 bis 1957 Ministerpräsident des Landes. Ab 1941 hatte er den Rang eines Feldmarschalls inne.",
    "year": 1897,
    "month": 7,
    "day": 14
  },
  {
    "name": "Buenaventura Durruti",
    "birthday": "1896-7-14",
    "thumbnail": {
      "source": "https://upload.wikimedia.org/wikipedia/commons/thumb/8/8f/Buenaventura_Durruti.jpg/240px-Buenaventura_Durruti.jpg",
      "width": 240,
      "height": 320
    },
    "extract": "Buenaventura Durruti Dumange war ein spanischer Anarchist, Syndikalist und Revolutionär. Als gewählter Führer einer republikanischen Elitekolonne war er eine der zentralen Figuren im Spanischen Bürgerkrieg.",
    "year": 1896,
    "month": 7,
    "day": 14
  },
  {
    "name": "Ossip Zadkine",
    "birthday": "1890-7-14",
    "thumbnail": {
      "source": "https://upload.wikimedia.org/wikipedia/commons/thumb/e/ef/Sandberg_Zadkine_1965_%28crop%2C_with_cigarette%29.jpg/320px-Sandberg_Zadkine_1965_%28crop%2C_with_cigarette%29.jpg",
      "width": 320,
      "height": 316
    },
    "extract": "Ossip Zadkine war ein weißrussisch-französischer Maler, Aquarellmaler und Bildhauer des Kubismus.",
    "year": 1890,
    "month": 7,
    "day": 14
  },
  {
    "name": "José López Alavez",
    "birthday": "1889-7-14",
    "thumbnail": {
      "source": "https://upload.wikimedia.org/wikipedia/commons/thumb/2/25/Canci%C3%B3n_Mixteca%2C_escultura_de_Juan_Velasco_ubicada_en_Quer%C3%A9taro.jpg/240px-Canci%C3%B3n_Mixteca%2C_escultura_de_Juan_Velasco_ubicada_en_Quer%C3%A9taro.jpg",
      "width": 240,
      "height": 320
    },
    "extract": "José López Alavez war ein mexikanischer Komponist.",
    "year": 1889,
    "month": 7,
    "day": 14
  },
  {
    "name": "Ante Pavelić",
    "birthday": "1889-7-14",
    "thumbnail": {
      "source": "https://upload.wikimedia.org/wikipedia/commons/thumb/7/78/Ante_Paveli%C4%87.jpg/215px-Ante_Paveli%C4%87.jpg",
      "width": 215,
      "height": 320
    },
    "extract": "Ante Pavelić war ein jugoslawischer Jurist, Politiker und Kriegsverbrecher. Von 1941 bis 1945 war er faschistischer Diktator des Unabhängigen Staates Kroatien (NDH).",
    "year": 1889,
    "month": 7,
    "day": 14
  },
  {
    "name": "Odiel Defraeye",
    "birthday": "1888-7-14",
    "thumbnail": {
      "source": "https://upload.wikimedia.org/wikipedia/commons/thumb/2/2d/Odiel_Defraeye.jpg/320px-Odiel_Defraeye.jpg",
      "width": 320,
      "height": 201
    },
    "extract": "Odilon „Odiel“ Defraeye war ein belgischer Radrennfahrer. Er war 1912 der erste belgische Gewinner einer Tour de France.",
    "year": 1888,
    "month": 7,
    "day": 14
  },
  {
    "name": "Satomi Ton",
    "birthday": "1888-7-14",
    "thumbnail": {
      "source": "https://upload.wikimedia.org/wikipedia/commons/thumb/5/5d/Satomi_Ton.jpg/202px-Satomi_Ton.jpg",
      "width": 202,
      "height": 320
    },
    "extract": "Satomi Ton war ein japanischer Schriftsteller.",
    "year": 1888,
    "month": 7,
    "day": 14
  },
  {
    "name": "Kakuza Tscholoqaschwili",
    "birthday": "1888-7-14",
    "thumbnail": {
      "source": "https://upload.wikimedia.org/wikipedia/commons/thumb/2/20/Kakutsa.jpg/233px-Kakutsa.jpg",
      "width": 233,
      "height": 320
    },
    "extract": "Kakuza (Kaichosro) Tscholoqaschwili war ein georgischer Offizier. 1919 war er stellvertretender Verteidigungsminister der ersten georgischen Republik. 1922 bis 1924 führte er Partisaneneinheiten gegen die sowjetische Besetzung Georgiens. Er gilt als georgischer Nationalheld.",
    "year": 1888,
    "month": 7,
    "day": 14
  },
  {
    "name": "Ernst Nobs",
    "birthday": "1886-7-14",
    "thumbnail": {
      "source": "https://upload.wikimedia.org/wikipedia/commons/a/a6/Ernst_Nobs.gif",
      "width": 160,
      "height": 200
    },
    "extract": "Ernst Nobs war ein Schweizer Politiker (SP) aus dem Kanton Zürich. Als Bundesrat war er Vorsteher des Finanzdepartements und bekleidete einmal das Amt des Bundespräsidenten. Er war 1943 der erste Sozialdemokrat überhaupt, der in die Landesregierung gewählt wurde.",
    "year": 1886,
    "month": 7,
    "day": 14
  },
  {
    "name": "Sisavang Vong",
    "birthday": "1885-7-14",
    "thumbnail": {
      "source": "https://upload.wikimedia.org/wikipedia/commons/thumb/b/b0/Sisavang_Vong_-_1951.jpg/192px-Sisavang_Vong_-_1951.jpg",
      "width": 192,
      "height": 320
    },
    "extract": "Sisavang Vong war von 1904 bis 1949 König des unter französischem Protektorat stehenden laotischen Königreichs Luang Prabang und anschließend bis 1959 König von Laos.",
    "year": 1885,
    "month": 7,
    "day": 14
  },
  {
    "name": "Karl Illner",
    "birthday": "1877-7-14",
    "thumbnail": {
      "source": "https://upload.wikimedia.org/wikipedia/commons/thumb/5/55/Karl_Illner_in_einem_flugzeug%2C_1913.jpg/320px-Karl_Illner_in_einem_flugzeug%2C_1913.jpg",
      "width": 320,
      "height": 208
    },
    "extract": "Karl Illner war ein österreichischer Flugpionier.",
    "year": 1877,
    "month": 7,
    "day": 14
  },
  {
    "name": "Loredana Cannata",
    "birthday": "1875-7-14",
    "thumbnail": {
      "source": "https://upload.wikimedia.org/wikipedia/commons/thumb/f/f4/Loredana_Cannata.jpg/192px-Loredana_Cannata.jpg",
      "width": 192,
      "height": 320
    },
    "extract": "Loredana Cannata ist eine italienische Schauspielerin.",
    "year": 1875,
    "month": 7,
    "day": 14
  },
  {
    "name": "Abbas II. (Ägypten)",
    "birthday": "1874-7-14",
    "thumbnail": {
      "source": "https://upload.wikimedia.org/wikipedia/commons/thumb/8/81/Abbas_Hilmi_II_colored.jpg/240px-Abbas_Hilmi_II_colored.jpg",
      "width": 240,
      "height": 320
    },
    "extract": "Abbas II., mit vollem Namen Abbas Hilmi Pascha war von 1892 bis 1914 der letzte Khedive (Vizekönig) des Khedivats Ägypten.",
    "year": 1874,
    "month": 7,
    "day": 14
  },
  {
    "name": "Irene Abendroth",
    "birthday": "1872-7-14",
    "thumbnail": {
      "source": "https://upload.wikimedia.org/wikipedia/commons/thumb/3/38/Irene_abendroth.jpg/263px-Irene_abendroth.jpg",
      "width": 263,
      "height": 320
    },
    "extract": "Irene Abendroth war eine österreichische Sängerin in der Stimmlage Koloratur-Sopran. Ihre weniger bekannte Schwester Mira Abendroth war ebenfalls eine Opernsängerin.",
    "year": 1872,
    "month": 7,
    "day": 14
  },
  {
    "name": "Gertrude Bell",
    "birthday": "1868-7-14",
    "thumbnail": {
      "source": "https://upload.wikimedia.org/wikipedia/commons/thumb/8/84/BellK_218_Gertrude_Bell_in_Iraq_in_1909_age_41.jpg/242px-BellK_218_Gertrude_Bell_in_Iraq_in_1909_age_41.jpg",
      "width": 242,
      "height": 320
    },
    "extract": "Gertrude Margaret Lowthian Bell CBE war eine britische Forschungsreisende, Historikerin, Schriftstellerin, Archäologin, Alpinistin, politische Beraterin und Angehörige des britischen Geheimdienstes im Ersten Weltkrieg. Aufgrund ihrer auf einer Reihe von Reisen gewonnenen Kenntnisse des Nahen Ostens spielte sie ebenso wie der als Lawrence von Arabien bekannt gewordene Thomas Edward Lawrence während des Ersten Weltkriegs und danach eine große Rolle in der politischen Neuordnung dieser Region. Bereits 1917 wurde sie für ihre Leistungen mit dem Order of the British Empire (CBE) ausgezeichnet. Als zunächst inoffizielle Mitarbeiterin des Secret Intelligence Service, später als politischer Verbindungsoffizier und Orientsekretärin war sie maßgeblich an der Gründung des heutigen Iraks beteiligt und gehörte zu den engen Vertrauten des irakischen Königs Faisal I. Auch an der Entstehung des Irakischen Nationalmuseums in Bagdad hatte sie wesentlichen Anteil.",
    "year": 1868,
    "month": 7,
    "day": 14
  },
  {
    "name": "Ragnar Östberg",
    "birthday": "1866-7-14",
    "thumbnail": {
      "source": "https://upload.wikimedia.org/wikipedia/commons/thumb/b/b1/Ragnar_%C3%96stberg_-_from_Svenskt_Portr%C3%A4ttgalleri_XX.png/237px-Ragnar_%C3%96stberg_-_from_Svenskt_Portr%C3%A4ttgalleri_XX.png",
      "width": 237,
      "height": 320
    },
    "extract": "Ragnar Östberg war ein schwedischer Architekt und Professor an der Kungliga Konsthögskolan Stockholm in den Jahren 1922 bis 1932.",
    "year": 1866,
    "month": 7,
    "day": 14
  },
  {
    "name": "Juliette Wytsman",
    "birthday": "1866-7-14",
    "thumbnail": {
      "source": "https://upload.wikimedia.org/wikipedia/commons/4/48/Portrait_of_Juliette_and_Rodolphe_Wytsman_%28cropped%29.Jpg",
      "width": 184,
      "height": 215
    },
    "extract": "Juliette Wytsman, geb. Trullemans war eine belgische Landschaftsmalerin. Sie gilt als eine der bedeutendsten Vertreterin des belgischen Impressionismus Ende des 19. bis Anfang des 20. Jahrhunderts.",
    "year": 1866,
    "month": 7,
    "day": 14
  },
  {
    "name": "Gustav Klimt",
    "birthday": "1862-7-14",
    "thumbnail": {
      "source": "https://upload.wikimedia.org/wikipedia/commons/thumb/a/a5/Gustav_Klimt_2012_Pressefoto09.jpg/320px-Gustav_Klimt_2012_Pressefoto09.jpg",
      "width": 320,
      "height": 236
    },
    "extract": "Gustav Klimt war ein bedeutender österreichischer Maler, bekanntester Vertreter des Wiener Jugendstils und Gründungspräsident der Wiener Secession.",
    "year": 1862,
    "month": 7,
    "day": 14
  },
  {
    "name": "Willy Hess (Violinist)",
    "birthday": "1859-7-14",
    "thumbnail": {
      "source": "https://upload.wikimedia.org/wikipedia/commons/thumb/8/8e/WillyHess.jpg/211px-WillyHess.jpg",
      "width": 211,
      "height": 320
    },
    "extract": "Willy Hess war ein deutscher Violinvirtuose und Violinlehrer.",
    "year": 1859,
    "month": 7,
    "day": 14
  },
  {
    "name": "Eduard Kullmann",
    "birthday": "1853-7-14",
    "thumbnail": {
      "source": "https://upload.wikimedia.org/wikipedia/commons/thumb/e/e5/Eduard_Kullmann.jpg/190px-Eduard_Kullmann.jpg",
      "width": 190,
      "height": 320
    },
    "extract": "Eduard Franz Ludwig Kullmann war ein deutscher Handwerker und wurde 1874 bekannt als Bismarck-Attentäter.",
    "year": 1853,
    "month": 7,
    "day": 14
  },
  {
    "name": "Ludwig von Tetmajer",
    "birthday": "1850-7-14",
    "thumbnail": {
      "source": "https://upload.wikimedia.org/wikipedia/commons/thumb/4/4c/Ludwig_von_Tetmajer_Bueste_Hof_TU_Wien-DSC_6752w.jpg/213px-Ludwig_von_Tetmajer_Bueste_Hof_TU_Wien-DSC_6752w.jpg",
      "width": 213,
      "height": 320
    },
    "extract": "Ludwig von Tetmajer \nwar Professor des Zürcher Polytechnikums und gilt als Pionier der Materialprüfung und -forschung und Begründer der Eidgenössischen Materialprüfungs- und Forschungsanstalt.",
    "year": 1850,
    "month": 7,
    "day": 14
  },
  {
    "name": "Gustav Eberlein",
    "birthday": "1847-7-14",
    "thumbnail": {
      "source": "https://upload.wikimedia.org/wikipedia/commons/thumb/c/c2/Gustav_Eberlein_%28BerlLeben_1903-10%29-var.jpg/320px-Gustav_Eberlein_%28BerlLeben_1903-10%29-var.jpg",
      "width": 320,
      "height": 283
    },
    "extract": "Gustav Heinrich Eberlein war ein deutscher Bildhauer, Maler und Schriftsteller. Er war um 1900 nach Reinhold Begas der meist beschäftigte Künstler der Berliner Bildhauerschule des 19. Jahrhunderts.",
    "year": 1847,
    "month": 7,
    "day": 14
  },
  {
    "name": "Alexander Linnemann",
    "birthday": "1839-7-14",
    "thumbnail": {
      "source": "https://upload.wikimedia.org/wikipedia/commons/thumb/6/60/Alexander_Linnemann.jpg/202px-Alexander_Linnemann.jpg",
      "width": 202,
      "height": 320
    },
    "extract": "Alexander Linnemann war ein deutscher Architekt, Glasmaler und Kunstgewerbler.",
    "year": 1839,
    "month": 7,
    "day": 14
  },
  {
    "name": "Caspar Joseph Brambach",
    "birthday": "1833-7-14",
    "thumbnail": {
      "source": "https://upload.wikimedia.org/wikipedia/commons/thumb/8/81/C_S_Brambach.jpg/197px-C_S_Brambach.jpg",
      "width": 197,
      "height": 320
    },
    "extract": "Caspar Joseph Brambach war ein deutscher Musiker und Komponist.",
    "year": 1833,
    "month": 7,
    "day": 14
  },
  {
    "name": "Henry Edward Bird",
    "birthday": "1830-7-14",
    "thumbnail": {
      "source": "https://upload.wikimedia.org/wikipedia/commons/d/db/Henry_Edward_Bird_%281877_drawing_by_Sam_Loyd%29.jpg",
      "width": 202,
      "height": 235
    },
    "extract": "Henry Edward Bird war einer der besten englischen Schachspieler des 19. Jahrhunderts.",
    "year": 1830,
    "month": 7,
    "day": 14
  },
  {
    "name": "Adolf Cluss",
    "birthday": "1825-7-14",
    "thumbnail": {
      "source": "https://upload.wikimedia.org/wikipedia/commons/thumb/0/0d/Cluss-adolf.jpg/221px-Cluss-adolf.jpg",
      "width": 221,
      "height": 320
    },
    "extract": "Adolf Ludwig Cluss war ein deutsch-amerikanischer Architekt. Er gehörte bis 1858 zum inneren Zirkel der Kommunisten um Karl Marx und Friedrich Engels und wurde nach 1864 zum bedeutendsten Architekten Washingtons.",
    "year": 1825,
    "month": 7,
    "day": 14
  },
  {
    "name": "Arthur de Gobineau",
    "birthday": "1816-7-14",
    "thumbnail": {
      "source": "https://upload.wikimedia.org/wikipedia/commons/thumb/5/5c/Arthur_de_Gobineau.jpg/251px-Arthur_de_Gobineau.jpg",
      "width": 251,
      "height": 320
    },
    "extract": "Joseph Arthur de Gobineau war ein französischer Diplomat und Schriftsteller. Seine allgemeine Bekanntheit verdankt er dem Versuch über die Ungleichheit der Menschenrassen. Er gilt deswegen als einer der Begründer des rassistischen Denkens. Daneben war er auch Autor spätromantischer Dichtungen, mehrerer polemischer Essays sowie der Verfasser von historischen und philologischen Arbeiten über das antike Persien.",
    "year": 1816,
    "month": 7,
    "day": 14
  },
  {
    "name": "Buenaventura Báez",
    "birthday": "1812-7-14",
    "thumbnail": {
      "source": "https://upload.wikimedia.org/wikipedia/commons/thumb/7/7e/Buenaventura_Ba%C3%A9z.gif/240px-Buenaventura_Ba%C3%A9z.gif",
      "width": 240,
      "height": 320
    },
    "extract": "Buenaventura Báez Méndez war fünfmaliger Präsident der Dominikanischen Republik.",
    "year": 1812,
    "month": 7,
    "day": 14
  },
  {
    "name": "Ventura de la Vega",
    "birthday": "1807-7-14",
    "thumbnail": {
      "source": "https://upload.wikimedia.org/wikipedia/commons/thumb/a/a6/Ventura_de_la_Vega_por_Federico_Madrazo.jpg/277px-Ventura_de_la_Vega_por_Federico_Madrazo.jpg",
      "width": 277,
      "height": 320
    },
    "extract": "Ventura de la Vega war ein ursprünglich aus Argentinien stammender Dramenautor und Librettist für Zarzuelas, der die meiste Zeit seines Lebens in Spanien verbrachte und deshalb meist zur spanischen Literatur gezählt wird.",
    "year": 1807,
    "month": 7,
    "day": 14
  },
  {
    "name": "Favell Lee Mortimer",
    "birthday": "1802-7-14",
    "thumbnail": {
      "source": "https://upload.wikimedia.org/wikipedia/commons/thumb/b/b5/Favell_Lee_Mortimer.jpg/191px-Favell_Lee_Mortimer.jpg",
      "width": 191,
      "height": 320
    },
    "extract": "Favell Lee Mortimer war eine englische Autorin von Sachbüchern für Kinder.",
    "year": 1802,
    "month": 7,
    "day": 14
  },
  {
    "name": "Johannes Müller (Mediziner)",
    "birthday": "1801-7-14",
    "thumbnail": {
      "source": "https://upload.wikimedia.org/wikipedia/commons/thumb/f/f0/Johannes_Peter_M%C3%BCller.jpg/241px-Johannes_Peter_M%C3%BCller.jpg",
      "width": 241,
      "height": 320
    },
    "extract": "Johannes Peter Müller war ein deutscher Mediziner, Physiologe und vergleichender Anatom bzw. Zoologe sowie Meeresbiologe und Naturphilosoph. Er befasste sich vor allem mit der Nerven- und Sinnesphysiologie, baute die Reflexlehre weiter aus und gilt als der bedeutendste Physiologe des 19. Jahrhunderts.",
    "year": 1801,
    "month": 7,
    "day": 14
  },
  {
    "name": "Alessandro Antonelli",
    "birthday": "1798-7-14",
    "thumbnail": {
      "source": "https://upload.wikimedia.org/wikipedia/commons/thumb/8/83/Alessandro-Antonelli.jpg/219px-Alessandro-Antonelli.jpg",
      "width": 219,
      "height": 320
    },
    "extract": "Alessandro Antonelli war ein italienischer Architekt und gilt als bedeutender Architekt des 19. Jahrhunderts.",
    "year": 1798,
    "month": 7,
    "day": 14
  },
  {
    "name": "Caroline Friedrich",
    "birthday": "1793-7-14",
    "thumbnail": {
      "source": "https://upload.wikimedia.org/wikipedia/commons/thumb/5/53/Caroline_Bommer.jpg/242px-Caroline_Bommer.jpg",
      "width": 242,
      "height": 320
    },
    "extract": "Caroline Friedrich war die Ehefrau des Malers Caspar David Friedrich.",
    "year": 1793,
    "month": 7,
    "day": 14
  },
  {
    "name": "Gottlob Christian Crusius",
    "birthday": "1785-7-14",
    "thumbnail": {
      "source": "https://upload.wikimedia.org/wikipedia/commons/thumb/d/db/Gottlob_Christian_Crusius.jpg/207px-Gottlob_Christian_Crusius.jpg",
      "width": 207,
      "height": 320
    },
    "extract": "Gottlob Christian Crusius war ein deutscher Philologe, Pädagoge und Autor.",
    "year": 1785,
    "month": 7,
    "day": 14
  },
  {
    "name": "Hans von Bülow (Politiker, 1774)",
    "birthday": "1774-7-14",
    "thumbnail": {
      "source": "https://upload.wikimedia.org/wikipedia/commons/thumb/c/cf/Graf_von_B%C3%BClow.JPG/264px-Graf_von_B%C3%BClow.JPG",
      "width": 264,
      "height": 320
    },
    "extract": "Ludwig Friedrich Victor Hans von Bülow, seit 1810/16 Graf von Bülow, war ein preußischer und westphälischer Staatsmann.",
    "year": 1774,
    "month": 7,
    "day": 14
  },
  {
    "name": "Ferdinand Hartmann (Maler)",
    "birthday": "1774-7-14",
    "thumbnail": {
      "source": "https://upload.wikimedia.org/wikipedia/commons/thumb/8/86/WP_Ferdinand_Hartmann.jpg/244px-WP_Ferdinand_Hartmann.jpg",
      "width": 244,
      "height": 320
    },
    "extract": "Christian Ferdinand Hartmann war Historienmaler und seit 1811 Mitglied der Preußischen Akademie der Künste, Berlin, in der Sektion für die Bildenden Künste.",
    "year": 1774,
    "month": 7,
    "day": 14
  },
  {
    "name": "Karl Asmund Rudolphi",
    "birthday": "1771-7-14",
    "thumbnail": {
      "source": "https://upload.wikimedia.org/wikipedia/commons/thumb/f/fd/Karl_Asmund_Rudolphi_Litho.JPG/211px-Karl_Asmund_Rudolphi_Litho.JPG",
      "width": 211,
      "height": 320
    },
    "extract": "Karl Asmund Rudolphi war ein in Schweden geborener deutscher Mediziner, Anatom und Physiologe, Botaniker und Zoologe. Sein offizielles botanisches Autorenkürzel lautet „Rudolphi“.",
    "year": 1771,
    "month": 7,
    "day": 14
  },
  {
    "name": "Joseph François Durutte",
    "birthday": "1767-7-14",
    "thumbnail": {
      "source": "https://upload.wikimedia.org/wikipedia/commons/thumb/9/98/General_Durutte_by_Fran%C3%A7ois_B%C3%B6hm_1.jpg/267px-General_Durutte_by_Fran%C3%A7ois_B%C3%B6hm_1.jpg",
      "width": 267,
      "height": 320
    },
    "extract": "Pierre François Joseph Durutte war Graf und französischer Général de division.",
    "year": 1767,
    "month": 7,
    "day": 14
  },
  {
    "name": "Pierre Dupont de l’Étang",
    "birthday": "1765-7-14",
    "thumbnail": {
      "source": "https://upload.wikimedia.org/wikipedia/commons/thumb/b/bc/General_Pierre_Dupont_de_l%27%C3%89tang.jpg/282px-General_Pierre_Dupont_de_l%27%C3%89tang.jpg",
      "width": 282,
      "height": 320
    },
    "extract": "Pierre Antoine Dupont de l’Étang war ein französischer General zur Zeit der französischen Revolution, unter Napoleon und dem restaurierten Königtum.",
    "year": 1765,
    "month": 7,
    "day": 14
  },
  {
    "name": "Aaron Arrowsmith",
    "birthday": "1750-7-14",
    "thumbnail": {
      "source": "https://upload.wikimedia.org/wikipedia/commons/7/71/Aaron_Arrowsmith.jpg",
      "width": 253,
      "height": 300
    },
    "extract": "Aaron Arrowsmith war ein englischer Kartograf, Graveur und Verleger sowie Gründer der Geografenfamilie Arrowsmith.",
    "year": 1750,
    "month": 7,
    "day": 14
  },
  {
    "name": "Frederik von Haxthausen",
    "birthday": "1750-7-14",
    "thumbnail": {
      "source": "https://upload.wikimedia.org/wikipedia/commons/thumb/c/c4/F_G_von_Haxthausen.png/232px-F_G_von_Haxthausen.png",
      "width": 232,
      "height": 320
    },
    "extract": "Frederik Gottschalk von Haxthausen war ein dänisch-norwegischer Offizier und Regierungsmitglied Norwegens.",
    "year": 1750,
    "month": 7,
    "day": 14
  },
  {
    "name": "Gawriil Romanowitsch Derschawin",
    "birthday": "1743-7-14",
    "thumbnail": {
      "source": "https://upload.wikimedia.org/wikipedia/commons/thumb/5/57/Derzhavin_by_Borovikovsky_%281811%2C_Pushkin_museum%29.jpg/252px-Derzhavin_by_Borovikovsky_%281811%2C_Pushkin_museum%29.jpg",
      "width": 252,
      "height": 320
    },
    "extract": "Gawriil Romanowitsch Derschawin war der bekannteste russische Poet vor Puschkin. Obwohl seine Werke der klassischen Literatur zugeordnet werden, sind seine besten Verse voller Antithesen und Widersprüche, die an John Donne und andere metaphysische Dichter erinnern.",
    "year": 1743,
    "month": 7,
    "day": 14
  },
  {
    "name": "Dirk Lohman",
    "birthday": "1730-7-14",
    "thumbnail": {
      "source": "https://upload.wikimedia.org/wikipedia/commons/thumb/7/71/4795292_Hage_Orgel.jpg/239px-4795292_Hage_Orgel.jpg",
      "width": 239,
      "height": 320
    },
    "extract": "Dirk Lohman war ostfriesischer Orgelbauer in Emden, der an zahlreichen Orgeln Ostfrieslands Reparaturen durchführte und in Hage (1776–1783) einen bedeutenden Neubau errichtete.",
    "year": 1730,
    "month": 7,
    "day": 14
  },
  {
    "name": "John Penn (Gouverneur)",
    "birthday": "1729-7-14",
    "thumbnail": {
      "source": "https://upload.wikimedia.org/wikipedia/commons/thumb/0/01/John_Penn%2C_colonial_governor_of_Pa_%28NYPL_NYPG94-F42-419831%29.jpg/218px-John_Penn%2C_colonial_governor_of_Pa_%28NYPL_NYPG94-F42-419831%29.jpg",
      "width": 218,
      "height": 320
    },
    "extract": "John Penn war der letzte Kolonial-Gouverneur Pennsylvanias. Er hatte dieses Amt von 1763 bis 1771 und von 1773 bis 1776 inne.",
    "year": 1729,
    "month": 7,
    "day": 14
  },
  {
    "name": "Caspar Abel",
    "birthday": "1676-7-14",
    "thumbnail": {
      "source": "https://upload.wikimedia.org/wikipedia/commons/thumb/3/3c/Caspar_Abel.JPG/197px-Caspar_Abel.JPG",
      "width": 197,
      "height": 320
    },
    "extract": "Caspar Abel war ein deutscher Historiker und plattdeutscher Dichter.",
    "year": 1676,
    "month": 7,
    "day": 14
  },
  {
    "name": "Joseph Abeille",
    "birthday": "1673-7-14",
    "thumbnail": {
      "source": "https://upload.wikimedia.org/wikipedia/commons/thumb/9/90/CdB_EauVive_930_3.jpg/320px-CdB_EauVive_930_3.jpg",
      "width": 320,
      "height": 215
    },
    "extract": "Joseph Abeille war ein französischer Architekt und Wasserbauingenieur.",
    "year": 1673,
    "month": 7,
    "day": 14
  },
  {
    "name": "Ferdinand Bonaventura I. von Harrach",
    "birthday": "1637-7-14",
    "thumbnail": {
      "source": "https://upload.wikimedia.org/wikipedia/commons/thumb/8/89/Harrach_zu_Rohrau_und_Thannhausen-Wappen.png/315px-Harrach_zu_Rohrau_und_Thannhausen-Wappen.png",
      "width": 315,
      "height": 320
    },
    "extract": "Ferdinand Bonaventura I. Reichsgraf von Harrach zu Rohrau, Freiherr zu Bruck und Pürrhenstein war ein österreichischer Adeliger, kaiserlicher Diplomat, Staatsmann, Kämmerer, wirklicher Geheimer Rat sowie Ritter des Ordens vom Goldenen Vlies. Er wurde 1673 zum Obersterblandstallmeister in Österreich ob und unter der Enns ernannt, wurde 1676 Gesandter in Spanien und nach seiner Rückkehr 1677 Geheimer Staatsrat. Im Jahre 1697 übernahm er als Botschafter am Spanischen Hof den wichtigsten diplomatischen Posten, da es darum ging, die Erbfolge nach König Karl II. von Spanien aus der spanischen Linie des Hauses Österreich für die österreichische Linie dieses Hauses in der Person von Erzherzog Karl von Österreich, den jüngeren Sohn von Kaiser Leopold I. insbesondere gegen französische und auch gegen bairische Ansprüche – durchzusetzen, was ihm trotz intensiver Bemühungen wegen entgegenstehender Machtinteressen europäischer Staaten letztlich nicht gelang.\nZurückgekehrt nach Wien wurde er zum 1698 zum kaiserlichen Obersthofmeister ernannt und wurde Direktor des geheimen Staats-Konferenzrates, übernahm damit den Vorsitz der Staatskonferenz und die Leitung der Außenpolitik. Er begleitete Kaiser Leopold I. 1705 bei dessen Ableben, nahm hochbetagt am 22. September 1705 an der Erbhuldigung für Kaiser Joseph I. teil und verstarb selbst am 15. Juni 1706 bei einer Kur in Karlsbad in Böhmen.\nIn Erinnerung blieb er als näherer Stammvater seiner Familie und als Erbauer des Palais Harrach in Wien, das 300 Jahre in Familienbesitz blieb.",
    "year": 1637,
    "month": 7,
    "day": 14
  },
  {
    "name": "Hedwig Sophie von Brandenburg",
    "birthday": "1623-7-14",
    "thumbnail": {
      "source": "https://upload.wikimedia.org/wikipedia/commons/thumb/6/6e/Hedvig_Sofia_de_Brandemburgo.jpg/250px-Hedvig_Sofia_de_Brandemburgo.jpg",
      "width": 250,
      "height": 320
    },
    "extract": "Hedwig Sophie von Brandenburg war die Frau des Landgrafen Wilhelm VI. von Hessen-Kassel und nach dessen Tod Regentin von Hessen-Kassel bis 1677.",
    "year": 1623,
    "month": 7,
    "day": 14
  },
  {
    "name": "Heinrich Bacmeister",
    "birthday": "1618-7-14",
    "thumbnail": {
      "source": "https://upload.wikimedia.org/wikipedia/commons/0/07/Heinrich_Bacmeister.jpg",
      "width": 225,
      "height": 317
    },
    "extract": "Heinrich Bacmeister war ein deutscher Oberjustizrat und Kammerprokurator.",
    "year": 1618,
    "month": 7,
    "day": 14
  },
  {
    "name": "Ferdinando II. de’ Medici",
    "birthday": "1610-7-14",
    "thumbnail": {
      "source": "https://upload.wikimedia.org/wikipedia/commons/thumb/4/45/Portrait_Ferdinando_II_de_Medici.jpg/262px-Portrait_Ferdinando_II_de_Medici.jpg",
      "width": 262,
      "height": 320
    },
    "extract": "Ferdinand II. war ein Großherzog von Toskana aus dem Hause der Medici.",
    "year": 1610,
    "month": 7,
    "day": 14
  },
  {
    "name": "Jules Mazarin",
    "birthday": "1602-7-14",
    "thumbnail": {
      "source": "https://upload.wikimedia.org/wikipedia/commons/thumb/7/7d/Cardinal_Mazarin_by_Pierre_Mignard_%28Mus%C3%A9e_Cond%C3%A9%29.jpg/272px-Cardinal_Mazarin_by_Pierre_Mignard_%28Mus%C3%A9e_Cond%C3%A9%29.jpg",
      "width": 272,
      "height": 320
    },
    "extract": "Jules Mazarin, eigentlich Giulio Mazzarino, er unterzeichnete aber bis zu seiner Übersiedlung nach Frankreich als Giulio Mazzarini,, war ein französischer Diplomat und Kardinal italienischer Abstammung, seit 1659 Herzog von Nevers und Rethel sowie von 1642 bis 1661 regierender Minister Frankreichs als Nachfolger von Kardinal Richelieu.",
    "year": 1602,
    "month": 7,
    "day": 14
  },
  {
    "name": "Philipp I. (Pommern)",
    "birthday": "1515-7-14",
    "thumbnail": {
      "source": "https://upload.wikimedia.org/wikipedia/commons/thumb/1/1a/Philipp_I._von_Pommern.png/219px-Philipp_I._von_Pommern.png",
      "width": 219,
      "height": 320
    },
    "extract": "Philipp I. war Herzog von Pommern-Wolgast. 1534 schloss sich ganz Pommern der Reformation an.",
    "year": 1515,
    "month": 7,
    "day": 14
  },
  {
    "name": "Angelo Poliziano",
    "birthday": "1454-7-14",
    "thumbnail": {
      "source": "https://upload.wikimedia.org/wikipedia/commons/thumb/7/73/Angelo_Poliziano_-_Angel_Appearing_to_Zacharias_%28detail%29.jpg/240px-Angelo_Poliziano_-_Angel_Appearing_to_Zacharias_%28detail%29.jpg",
      "width": 240,
      "height": 320
    },
    "extract": "Angelo Poliziano war ein italienischer Humanist und Dichter der Renaissance. Seine Werke waren maßgeblich für die Entstehung des humanistischen Lateins.",
    "year": 1454,
    "month": 7,
    "day": 14
  },
  {
    "name": "Philipp (Pfalz)",
    "birthday": "1448-7-14",
    "thumbnail": {
      "source": "https://upload.wikimedia.org/wikipedia/commons/thumb/0/01/Pfalzgraf_Philipp_I_%281448-1508%29_as_donor%2C_from_St._Cacilien_in_Neckarsteinach%2C_Middle_Rhine_-_Pfalz%2C_1483_AD%2C_stained_and_painted_glass_-_Hessisches_Landesmuseum_Darmstadt_-_Darmstadt%2C_Germany_-_DSC00614.jpg/192px-thumbnail.jpg",
      "width": 192,
      "height": 320
    },
    "extract": "Philipp der Aufrichtige, auch Philipp der Edelmütige und Philipp I., Pfalzgraf bei Rhein genannt aus der Familie der Wittelsbacher war Pfalzgraf und von 1476 bis 1508 Kurfürst von der Pfalz.",
    "year": 1448,
    "month": 7,
    "day": 14
  },
  {
    "name": "Arnold von Egmond",
    "birthday": "1410-7-14",
    "thumbnail": {
      "source": "https://upload.wikimedia.org/wikipedia/commons/thumb/0/08/Arnold_van_Egmond.jpg/227px-Arnold_van_Egmond.jpg",
      "width": 227,
      "height": 320
    },
    "extract": "Arnold von Egmond, aus dem Haus Egmond, war von 1423 bis 1465 sowie 1471 bis 1473 Herzog von Geldern.",
    "year": 1410,
    "month": 7,
    "day": 14
  },
  {
    "name": "Obizzo III. d’Este",
    "birthday": "1294-7-14",
    "thumbnail": {
      "source": "https://upload.wikimedia.org/wikipedia/commons/6/61/Obizzo_III_d%27Este2.jpg",
      "width": 286,
      "height": 304
    },
    "extract": "Obizzo III. d’Este aus der Familie Este war seit 1335 Herr von Ferrara und ab 1336 von Modena.",
    "year": 1294,
    "month": 7,
    "day": 14
  }
]